README.md
setup.cfg
setup.py
aiops/__init__.py
aiops/constants.py
aiops.egg-info/PKG-INFO
aiops.egg-info/SOURCES.txt
aiops.egg-info/dependency_links.txt
aiops.egg-info/requires.txt
aiops.egg-info/top_level.txt
aiops/config/__init__.py
aiops/demos/FourClassTextClassification.py
aiops/demos/__init__.py
aiops/pretrained/__init__.py
aiops/pretrained/models/__init__.py
aiops/pretrained/models/bert_vanilla_classifier.py
aiops/pretrained/models/bert_with_gru_classifier.py
aiops/pretrained/models/training.py
aiops/pretrained/pipelines/__init__.py
aiops/utils/__init__.py
aiops/utils/data_augmentation/__init__.py
aiops/utils/data_augmentation/bert.py
aiops/utils/text_preprocessing/__init__.py
aiops/utils/text_preprocessing/bert.py
aiops/utils/text_preprocessing/cleaning.py
aiops/utils/text_preprocessing/mask_conf.py
aiops/utils/text_preprocessing/parser.py
aiops/utils/text_preprocessing/replace_conf.py