Metadata-Version: 2.1
Name: aiops
Version: 0.0.0.53
Summary: Basic Utilities for aiops implementations
Home-page: https://github.com/amandeep1991/aiops
Author: Amandeep
Author-email: deep.aman91@gmail.com
License: MIT
Download-URL: https://github.com/amandeep1991/aiops/archive/0.0.0.53.tar.gz
Keywords: aiops,AI for Ops,AI for operations
Platform: UNKNOWN
Classifier: Development Status :: 3 - Alpha
Classifier: Intended Audience :: Developers
Classifier: Topic :: Software Development :: Build Tools
Classifier: License :: OSI Approved :: MIT License
Classifier: Programming Language :: Python :: 3.7
